pyrake-0.2.0.data/scripts/snake
pyrake-0.2.0.dist-info/DESCRIPTION.rst
pyrake-0.2.0.dist-info/METADATA
pyrake-0.2.0.dist-info/RECORD
pyrake-0.2.0.dist-info/WHEEL
pyrake-0.2.0.dist-info/metadata.json
pyrake-0.2.0.dist-info/top_level.txt
snake/__init__.py
snake/application.py
snake/datastructures.py
snake/dependencies.py
snake/parser.py
snake/shell.py
snake/tasks.py
snake/version.py
