Metadata-Version: 2.0
Name: pyrake
Version: 0.2.0
Summary: An easy to use build script utility
Home-page: https://github.com/jcomo/snake
Author: Jonathan Como
Author-email: jonathan.como@gmail.com
License: UNKNOWN
Keywords: python build automation script
Platform: UNKNOWN
Classifier: Programming Language :: Python :: 2
Classifier: Programming Language :: Python :: 2.6
Classifier: Programming Language :: Python :: 2.7
Classifier: Programming Language :: Python :: 3.3
Classifier: Programming Language :: Python :: 3.4
